<instance version="6" description="Unique Unit" template="ebps">
	<list name="extensions">
		<template_reference name="exts" value="ebpextensions\entity_blueprint_ext" List.ItemID="-765163162" List.ParentItemID="-765163162">
			<float name="entity_scale" value="80" overrideParent="True" />
		</template_reference>
		<template_reference name="exts" value="ebpextensions\type_ext" List.ItemID="-782585427" List.ParentItemID="-782585427">
			<list name="race_type_list" overrideParent="True">
				<instance_reference name="race_type" value="racebps\campaign\lithuania" List.ItemID="-872981790" />
			</list>
		</template_reference>
		<template_reference name="exts" value="ebpextensions\combat_ext" List.ItemID="1697644820" List.ParentItemID="1697644820">
			<list name="hardpoints">
				<group name="hardpoint" List.ItemID="1781403471" List.ParentItemID="1781403471">
					<list name="weapon_table">
						<group name="weapon" List.ItemID="-955194656" List.ParentItemID="-955194656">
							<template_reference name="weapon_entity_attachment" value="" overrideParent="True">
							</template_reference>
							<template_reference name="non_entity_weapon_wrapper" value="non_entity_weapon_wrapper" overrideParent="True">
								<instance_reference name="non_entity_weapon_wrapper_pbg" value="weapon\races\hre\melee\weapon_landsknecht_3_hre" overrideParent="True" />
								<instance_reference name="animator_attachments" value="attachments\attachment_lists\races\hre\weapons\wpn_melee_landsknecht_hre" overrideParent="True" />
								<string name="marker_name_parent" value="MetaRig_RArmPalmSocket" overrideParent="True" />
							</template_reference>
						</group>
						<group name="weapon" List.ItemID="-471332549" List.ParentItemID="-471332549">
							<template_reference name="weapon_entity_attachment" value="" overrideParent="True">
							</template_reference>
							<template_reference name="non_entity_weapon_wrapper" value="non_entity_weapon_wrapper" overrideParent="True">
								<instance_reference name="non_entity_weapon_wrapper_pbg" value="weapon\races\common\ranged\weapon_torch" overrideParent="True" />
								<instance_reference name="animator_attachments" value="attachments\attachment_lists\races\hre\weapons\wpn_siege_torch_hre" overrideParent="True" />
								<string name="marker_name_parent" value="MetaRig_RArmPalmSocket" overrideParent="True" />
							</template_reference>
						</group>
						<group name="weapon" List.ItemID="667584923" List.ParentItemID="667584923">
							<template_reference name="weapon_entity_attachment" value="" overrideParent="True">
							</template_reference>
							<template_reference name="non_entity_weapon_wrapper" value="non_entity_weapon_wrapper" overrideParent="True">
								<instance_reference name="non_entity_weapon_wrapper_pbg" value="weapon\races\hre\melee\weapon_landsknecht_3_charge_hre" overrideParent="True" />
								<instance_reference name="animator_attachments" value="attachments\attachment_lists\races\hre\weapons\wpn_melee_landsknecht_charge_hre" overrideParent="True" />
								<string name="marker_name_parent" value="MetaRig_RArmPalmSocket" overrideParent="True" />
							</template_reference>
						</group>
					</list>
				</group>
			</list>
		</template_reference>
		<template_reference name="exts" value="ebpextensions\tier_ext" List.ItemID="1590686263" List.ParentItemID="1590686263">
			<list name="tier_group_list">
				<list name="tier_group" List.ItemID="1642663640" List.ParentItemID="1642663640">
					<group name="tier" List.ItemID="1474675562" List.ParentItemID="1474675562">
						<instance_reference name="statetree_tier_pgb_upgrade_target_entity" value="ebps\races\campaign\lithuania\units\unit_landsknecht_4_lith" mod="e2ef01ea17d74b04949857ca0a246ab4" overrideParent="True" />
						<instance_reference name="statetree_tier_pgb_upgrade_target_squad" value="sbps\races\campaign\lithuania\unit_landsknecht_4_lith" overrideParent="True" />
					</group>
				</list>
			</list>
		</template_reference>
	</list>
	<uniqueid name="pbgid" value="183000" />
	<instance_reference name="parent_pbg" value="ebps\races\hre\units\unit_landsknecht_3_hre" />
	<variant name="campaign">
		<list name="extensions">
			<template_reference name="exts" value="ebpextensions\type_ext" List.ItemID="1104798827" List.ParentItemID="1104798827">
				<list name="race_type_list" overrideParent="True">
					<instance_reference name="race_type" value="racebps\campaign\lithuania" List.ItemID="-969451632" />
				</list>
			</template_reference>
			<template_reference name="exts" value="ebpextensions\combat_ext" List.ItemID="288926342" List.ParentItemID="288926342">
				<list name="hardpoints">
					<group name="hardpoint" List.ItemID="-1042324492" List.ParentItemID="-1042324492">
						<list name="weapon_table">
							<group name="weapon" List.ItemID="306288311" List.ParentItemID="306288311">
								<template_reference name="weapon_entity_attachment" value="" overrideParent="True">
								</template_reference>
								<template_reference name="non_entity_weapon_wrapper" value="non_entity_weapon_wrapper" overrideParent="True">
									<instance_reference name="non_entity_weapon_wrapper_pbg" value="weapon\races\hre\melee\weapon_landsknecht_3_hre" overrideParent="True" />
									<instance_reference name="animator_attachments" value="attachments\attachment_lists\races\hre\weapons\wpn_melee_landsknecht_hre" overrideParent="True" />
									<string name="marker_name_parent" value="MetaRig_RArmPalmSocket" overrideParent="True" />
								</template_reference>
							</group>
							<group name="weapon" List.ItemID="1265922142" List.ParentItemID="1265922142">
								<template_reference name="weapon_entity_attachment" value="" overrideParent="True">
								</template_reference>
								<template_reference name="non_entity_weapon_wrapper" value="non_entity_weapon_wrapper" overrideParent="True">
									<instance_reference name="non_entity_weapon_wrapper_pbg" value="weapon\races\common\ranged\weapon_torch" overrideParent="True" />
									<instance_reference name="animator_attachments" value="attachments\attachment_lists\races\hre\weapons\wpn_siege_torch_hre" overrideParent="True" />
									<string name="marker_name_parent" value="MetaRig_RArmPalmSocket" overrideParent="True" />
								</template_reference>
							</group>
							<group name="weapon" List.ItemID="-1536951353" List.ParentItemID="-1536951353">
								<template_reference name="weapon_entity_attachment" value="" overrideParent="True">
								</template_reference>
								<template_reference name="non_entity_weapon_wrapper" value="non_entity_weapon_wrapper" overrideParent="True">
									<instance_reference name="non_entity_weapon_wrapper_pbg" value="weapon\races\hre\melee\weapon_landsknecht_3_charge_hre" overrideParent="True" />
									<instance_reference name="animator_attachments" value="attachments\attachment_lists\races\hre\weapons\wpn_melee_landsknecht_charge_hre" overrideParent="True" />
									<string name="marker_name_parent" value="MetaRig_RArmPalmSocket" overrideParent="True" />
								</template_reference>
							</group>
						</list>
					</group>
				</list>
			</template_reference>
			<template_reference name="exts" value="ebpextensions\tier_ext" List.ItemID="202880116" List.ParentItemID="202880116">
				<list name="tier_group_list">
					<list name="tier_group" List.ItemID="641209622" List.ParentItemID="641209622">
						<group name="tier" List.ItemID="-1090230634" List.ParentItemID="-1090230634">
							<instance_reference name="statetree_tier_pgb_upgrade_target_entity" value="ebps\races\campaign\lithuania\units\unit_landsknecht_4_lith" mod="e2ef01ea17d74b04949857ca0a246ab4" overrideParent="True" />
							<instance_reference name="statetree_tier_pgb_upgrade_target_squad" value="sbps\races\campaign\lithuania\unit_landsknecht_4_lith" overrideParent="True" />
						</group>
					</list>
				</list>
			</template_reference>
		</list>
		<uniqueid name="pbgid" value="183000" />
		<instance_reference name="parent_pbg" value="ebps\races\hre\units\unit_landsknecht_3_hre" />
	</variant>
</instance>